{
  "indexes": [
    {
      "collectionGroup": "engagement",
      "queryScope": "COLLECTION",
      "fields": [
        { "fieldPath": "hasReachedEnd", "order": "ASCENDING" },
        { "fieldPath": "updatedAt", "order": "DESCENDING" }
      ]
    },
    {
      "collectionGroup": "artifacts",
      "queryScope": "COLLECTION",
      "fields": [
        { "fieldPath": "emotion", "order": "ASCENDING" },
        { "fieldPath": "isPublic", "order": "ASCENDING" },
        { "fieldPath": "createdAt", "order": "DESCENDING" },
        { "fieldPath": "__name__", "order": "DESCENDING" }
      ]
    },
    {
      "collectionGroup": "artifacts",
      "queryScope": "COLLECTION",
      "fields": [
        { "fieldPath": "isPublic", "order": "ASCENDING" },
        { "fieldPath": "createdAt", "order": "DESCENDING" },
        { "fieldPath": "__name__", "order": "DESCENDING" }
      ]
    },
    {
      "collectionGroup": "artifacts",
      "queryScope": "COLLECTION",
      "fields": [
        { "fieldPath": "isPublic", "order": "ASCENDING" },
        { "fieldPath": "status", "order": "ASCENDING" },
        { "fieldPath": "createdAt", "order": "DESCENDING" },
        { "fieldPath": "__name__", "order": "DESCENDING" }
      ]
    },
    {
      "collectionGroup": "artifacts",
      "queryScope": "COLLECTION",
      "fields": [
        { "fieldPath": "isPublic", "order": "ASCENDING" },
        { "fieldPath": "timestamp", "order": "DESCENDING" },
        { "fieldPath": "__name__", "order": "DESCENDING" }
      ]
    },
    {
      "collectionGroup": "artifacts",
      "queryScope": "COLLECTION",
      "fields": [
        { "fieldPath": "userId", "order": "ASCENDING" },
        { "fieldPath": "createdAt", "order": "DESCENDING" },
        { "fieldPath": "__name__", "order": "DESCENDING" }
      ]
    },
    {
      "collectionGroup": "listening_sessions",
      "queryScope": "COLLECTION",
      "fields": [
        { "fieldPath": "userId", "order": "ASCENDING" },
        { "fieldPath": "isCompleted", "order": "ASCENDING" },
        { "fieldPath": "updatedAt", "order": "DESCENDING" },
        { "fieldPath": "__name__", "order": "DESCENDING" }
      ]
    },
    {
      "collectionGroup": "notifications",
      "queryScope": "COLLECTION",
      "fields": [
        { "fieldPath": "userId", "order": "ASCENDING" },
        { "fieldPath": "createdAt", "order": "DESCENDING" },
        { "fieldPath": "__name__", "order": "DESCENDING" }
      ]
    },
    {
      "collectionGroup": "reactions_global",
      "queryScope": "COLLECTION",
      "fields": [
        { "fieldPath": "userId", "order": "ASCENDING" },
        { "fieldPath": "timestamp", "order": "DESCENDING" },
        { "fieldPath": "__name__", "order": "DESCENDING" }
      ]
    },
    {
      "collectionGroup": "comments",
      "queryScope": "COLLECTION",
      "fields": [
        { "fieldPath": "artifactId", "order": "ASCENDING" },
        { "fieldPath": "artifactOwnerId", "order": "ASCENDING" },
        { "fieldPath": "authorId", "order": "ASCENDING" },
        { "fieldPath": "createdAt", "order": "DESCENDING" },
        { "fieldPath": "__name__", "order": "DESCENDING" }
      ]
    },
    {
      "collectionGroup": "comments",
      "queryScope": "COLLECTION",
      "fields": [
        { "fieldPath": "artifactId", "order": "ASCENDING" },
        { "fieldPath": "artifactOwnerId", "order": "ASCENDING" },
        { "fieldPath": "visibilityLayer", "order": "ASCENDING" },
        { "fieldPath": "createdAt", "order": "DESCENDING" },
        { "fieldPath": "__name__", "order": "DESCENDING" }
      ]
    }
  ],
  "fieldOverrides": []
}
